napari_validate_random_label_predictions/__init__.py
napari_validate_random_label_predictions/_version.py
napari_validate_random_label_predictions/_widget.py
napari_validate_random_label_predictions/napari.yaml
napari_validate_random_label_predictions/_tests/__init__.py
napari_validate_random_label_predictions/_tests/test_widget.py
napari_validate_random_label_predictions-0.0.1.dist-info/LICENSE
napari_validate_random_label_predictions-0.0.1.dist-info/METADATA
napari_validate_random_label_predictions-0.0.1.dist-info/WHEEL
napari_validate_random_label_predictions-0.0.1.dist-info/entry_points.txt
napari_validate_random_label_predictions-0.0.1.dist-info/top_level.txt
napari_validate_random_label_predictions-0.0.1.dist-info/RECORD
